google_payment_token_decipher/__init__.py
google_payment_token_decipher/exceptions.py
google_payment_token_decipher/models.py
google_payment_token_decipher/public_key_manager.py
google_payment_token_decipher/version.py
google_payment_token_decipher-0.0.1.dist-info/LICENSE
google_payment_token_decipher-0.0.1.dist-info/METADATA
google_payment_token_decipher-0.0.1.dist-info/WHEEL
google_payment_token_decipher-0.0.1.dist-info/top_level.txt
google_payment_token_decipher-0.0.1.dist-info/RECORD
